fancyTextTools/__init__.py
fancyTextTools/fancyTextTools.py
textTools/__init__.py
fancyTextTools-1.2.0.dist-info/METADATA
fancyTextTools-1.2.0.dist-info/WHEEL
fancyTextTools-1.2.0.dist-info/top_level.txt
fancyTextTools-1.2.0.dist-info/RECORD
