Metadata-Version: 2.1
Name: fancyTextTools
Version: 1.2.0
Summary: A fancyTextTools Python package
Home-page: https://github.com/becker63/textTools
Author: Taylor Johnson
Author-email: johnsontaylor6320@gmail.com
License: BSD 2-clause
Platform: UNKNOWN
Classifier: Development Status :: 1 - Planning
Classifier: Intended Audience :: Science/Research
Classifier: License :: OSI Approved :: BSD License
Classifier: Operating System :: POSIX :: Linux
Classifier: Programming Language :: Python :: 2
Classifier: Programming Language :: Python :: 2.7
Classifier: Programming Language :: Python :: 3
Classifier: Programming Language :: Python :: 3.4
Classifier: Programming Language :: Python :: 3.5
